[{"product":"http://www.ratingsite0.fr/Product105987","label":"\"Ozymandias\""},{"product":"http://www.ratingsite32.fr/Product105987","label":"\"Ozymandias\""},{"product":"http://www.ratingsite45.fr/Product105987","label":"\"Ozymandias\""},{"product":"http://www.ratingsite55.fr/Product105987","label":"\"Ozymandias\""},{"product":"http://www.ratingsite57.fr/Product105987","label":"\"Ozymandias\""},{"product":"http://www.ratingsite97.fr/Product105987","label":"\"Ozymandias\""},{"product":"http://www.vendor30.fr/Product105987","label":"\"Ozymandias\""}]